linton/__init__.py
linton/__main__.py
linton/warnings_util.py
linton/init-pages/Author.in.txt
linton/init-pages/Email.in.txt
linton/init-pages/Title.in.txt
linton/init-pages/body.in.md
linton/init-pages/breadcrumb.in.py
linton/init-pages/email.in.py
linton/init-pages/favicon.png
linton/init-pages/index.nancy.html
linton/init-pages/lastmodified.in.py
linton/init-pages/markdown-to-html.in.py
linton/init-pages/menudirectory.in.py
linton/init-pages/pageinsite.in.py
linton/init-pages/path-to-root.in.py
linton/init-pages/style.css
linton/init-pages/template.in.html
linton/init-pages/Colophon/body.in.md
linton/init-pages/Colophon/index.nancy.html
linton/init-pages/Licence/body.in.md
linton/init-pages/Licence/index.nancy.html
linton/init-pages/Sample page/body.in.md
linton/init-pages/Sample page/index.nancy.html
linton/subcommand/init.py
linton/subcommand/publish.py
linton/subcommand/serve.py
linton-1.7.6.dist-info/licenses/COPYING
linton-1.7.6.dist-info/METADATA
linton-1.7.6.dist-info/WHEEL
linton-1.7.6.dist-info/entry_points.txt
linton-1.7.6.dist-info/top_level.txt
linton-1.7.6.dist-info/RECORD
