Metadata-Version: 2.4
Name: linton
Version: 1.7.6
Summary: Simple standalone static web site builder using Markdown
Author-email: Reuben Thomas <rrt@sc3d.org>
License-Expression: GPL-3.0-or-later
Project-URL: Homepage, https://github.com/rrthomas/linton
Classifier: Environment :: Console
Classifier: Programming Language :: Python :: 3
Requires-Python: >=3.10
License-File: COPYING
Requires-Dist: importlib_resources>=5.10
Requires-Dist: linkchecker
Requires-Dist: nancy~=11.0
Requires-Dist: mistletoe
Provides-Extra: test
Requires-Dist: pytest; extra == "test"
Dynamic: license-file
